faabrickmap_data/__init__.py
faabrickmap_data/admin.py
faabrickmap_data/apps.py
faabrickmap_data/djangoldp_urls.py
faabrickmap_data/models.py
faabrickmap_data/tests.py
faabrickmap_data/views.py
faabrickmap_data/management/commands/import_csv.py
faabrickmap_data/migrations/0001_initial.py
faabrickmap_data/migrations/0002_auto_20200130_2128.py
faabrickmap_data/migrations/0003_auto_20200210_1033.py
faabrickmap_data/migrations/0004_auto_20200210_1440.py
faabrickmap_data/migrations/0005_auto_20200210_1644.py
faabrickmap_data/migrations/0006_auto_20200226_1603.py
faabrickmap_data/migrations/0007_societe_logo2.py
faabrickmap_data/migrations/0008_auto_20200228_1709.py
faabrickmap_data/migrations/0009_auto_20200305_1147.py
faabrickmap_data/migrations/0010_auto_20200305_1150.py
faabrickmap_data/migrations/0011_societe_dpt.py
faabrickmap_data/migrations/0012_auto_20210511_1652.py
faabrickmap_data/migrations/0013_auto_20210511_1716.py
faabrickmap_data/migrations/0014_auto_20210511_1726.py
faabrickmap_data/migrations/0015_auto_20210511_2035.py
faabrickmap_data/migrations/__init__.py
faabrickmap_data/templates/index.html
faabrickmap_data/templates/export/template.xlsx
faabrickmap_data-1.0.11.dist-info/METADATA
faabrickmap_data-1.0.11.dist-info/WHEEL
faabrickmap_data-1.0.11.dist-info/top_level.txt
faabrickmap_data-1.0.11.dist-info/RECORD
