Metadata-Version: 2.1
Name: faabrickmap-data
Version: 1.0.11
Summary: StartinBlox specific FaabrickMap package
Home-page: UNKNOWN
License: MIT
Platform: UNKNOWN
Classifier: Programming Language :: Python :: 3
Requires-Dist: geopy (~=2.1)
